constant2/__init__.py
constant2/__init__.pyc
constant2/_constant2.py
constant2/_constant2.pyc
constant2/pkg/__init__.py
constant2/pkg/__init__.pyc
constant2/pkg/pylru.py
constant2/pkg/pylru.pyc
constant2/pkg/pytest.py
constant2/pkg/pytest.pyc
constant2/pkg/sixmini.py
constant2/pkg/sixmini.pyc
constant2/pkg/inspect_mate/__init__.py
constant2/pkg/inspect_mate/__init__.pyc
constant2/pkg/inspect_mate/getter.py
constant2/pkg/inspect_mate/getter.pyc
constant2/pkg/inspect_mate/tester.py
constant2/pkg/inspect_mate/tester.pyc
constant2/pkg/inspect_mate/tests/__init__.py
constant2/pkg/superjson/__init__.py
constant2/pkg/superjson/__init__.pyc
constant2/pkg/superjson/_superjson.py
constant2/pkg/superjson/_superjson.pyc
constant2/pkg/superjson/comments.py
constant2/pkg/superjson/comments.pyc
constant2/pkg/superjson/warning.py
constant2/pkg/superjson/warning.pyc
constant2/pkg/superjson/pkg/__init__.py
constant2/pkg/superjson/pkg/__init__.pyc
constant2/pkg/superjson/pkg/atomicwrites.py
constant2/pkg/superjson/pkg/atomicwrites.pyc
constant2/pkg/superjson/pkg/compresslib.py
constant2/pkg/superjson/pkg/compresslib.pyc
constant2/pkg/superjson/pkg/six.py
constant2/pkg/superjson/pkg/six.pyc
constant2/pkg/superjson/pkg/dateutil/__init__.py
constant2/pkg/superjson/pkg/dateutil/__init__.pyc
constant2/pkg/superjson/pkg/dateutil/_common.py
constant2/pkg/superjson/pkg/dateutil/_common.pyc
constant2/pkg/superjson/pkg/dateutil/_version.py
constant2/pkg/superjson/pkg/dateutil/_version.pyc
constant2/pkg/superjson/pkg/dateutil/easter.py
constant2/pkg/superjson/pkg/dateutil/parser.py
constant2/pkg/superjson/pkg/dateutil/parser.pyc
constant2/pkg/superjson/pkg/dateutil/relativedelta.py
constant2/pkg/superjson/pkg/dateutil/relativedelta.pyc
constant2/pkg/superjson/pkg/dateutil/rrule.py
constant2/pkg/superjson/pkg/dateutil/tzwin.py
constant2/pkg/superjson/pkg/dateutil/pkg/__init__.py
constant2/pkg/superjson/pkg/dateutil/pkg/__init__.pyc
constant2/pkg/superjson/pkg/dateutil/pkg/six.py
constant2-0.0.13.dist-info/LICENSE.txt
constant2-0.0.13.dist-info/METADATA
constant2-0.0.13.dist-info/WHEEL
constant2-0.0.13.dist-info/top_level.txt
constant2-0.0.13.dist-info/RECORD
